merge3/__init__.py
merge3/__main__.py
merge3/py.typed
merge3-0.0.16.dist-info/licenses/AUTHORS
merge3-0.0.16.dist-info/licenses/COPYING
merge3-0.0.16.dist-info/METADATA
merge3-0.0.16.dist-info/WHEEL
merge3-0.0.16.dist-info/entry_points.txt
merge3-0.0.16.dist-info/top_level.txt
merge3-0.0.16.dist-info/RECORD
