Metadata-Version: 2.4
Name: merge3
Version: 0.0.16
Summary: Python implementation of 3-way merge
Maintainer-email: Breezy Developers <team@breezy-vcs.org>
License-Expression: GPL-2.0-or-later
Project-URL: Homepage, https://www.breezy-vcs.org/
Project-URL: GitHub, https://github.com/breezy-team/merge3
Classifier: Development Status :: 4 - Beta
Classifier: Programming Language :: Python :: 3.9
Classifier: Programming Language :: Python :: 3.10
Classifier: Programming Language :: Python :: 3.11
Classifier: Programming Language :: Python :: 3.12
Classifier: Programming Language :: Python :: 3.13
Classifier: Programming Language :: Python :: 3.14
Classifier: Programming Language :: Python :: Implementation :: CPython
Classifier: Programming Language :: Python :: Implementation :: PyPy
Classifier: Operating System :: POSIX
Requires-Python: >=3.9
License-File: COPYING
License-File: AUTHORS
Provides-Extra: dev
Requires-Dist: ruff==0.14.0; extra == "dev"
Requires-Dist: mypy>=1.0.0; extra == "dev"
Dynamic: license-file
